{
  "$schema": "https://tree-sitter.github.io/tree-sitter/assets/schemas/grammar.schema.json",
  "name": "jai",
  "word": "identifier",
  "rules": {
    "source_file": {
      "type": "REPEAT",
      "content": {
        "type": "SYMBOL",
        "name": "_definition"
      }
    },
    "_definition": {
      "type": "PREC",
      "value": 1,
      "content": {
        "type": "CHOICE",
        "members": [
          {
            "type": "SYMBOL",
            "name": "import_directive"
          },
          {
            "type": "SYMBOL",
            "name": "proc_definition"
          },
          {
            "type": "SYMBOL",
            "name": "struct_definition"
          },
          {
            "type": "SYMBOL",
            "name": "enum_definition"
          },
          {
            "type": "SYMBOL",
            "name": "constant"
          },
          {
            "type": "SYMBOL",
            "name": "variable"
          },
          {
            "type": "SYMBOL",
            "name": "scope_module"
          },
          {
            "type": "SYMBOL",
            "name": "scope_file"
          },
          {
            "type": "SYMBOL",
            "name": "scope_export"
          },
          {
            "type": "SYMBOL",
            "name": "if_directive"
          },
          {
            "type": "SYMBOL",
            "name": "if_case_directive"
          }
        ]
      }
    },
    "scope_module": {
      "type": "SEQ",
      "members": [
        {
          "type": "STRING",
          "value": "#scope_module"
        },
        {
          "type": "CHOICE",
          "members": [
            {
              "type": "STRING",
              "value": ";"
            },
            {
              "type": "BLANK"
            }
          ]
        }
      ]
    },
    "scope_file": {
      "type": "SEQ",
      "members": [
        {
          "type": "STRING",
          "value": "#scope_file"
        },
        {
          "type": "CHOICE",
          "members": [
            {
              "type": "STRING",
              "value": ";"
            },
            {
              "type": "BLANK"
            }
          ]
        }
      ]
    },
    "scope_export": {
      "type": "SEQ",
      "members": [
        {
          "type": "STRING",
          "value": "#scope_export"
        },
        {
          "type": "CHOICE",
          "members": [
            {
              "type": "STRING",
              "value": ";"
            },
            {
              "type": "BLANK"
            }
          ]
        }
      ]
    },
    "struct_definition": {
      "type": "SEQ",
      "members": [
        {
          "type": "FIELD",
          "name": "name",
          "content": {
            "type": "SYMBOL",
            "name": "identifier"
          }
        },
        {
          "type": "STRING",
          "value": "::"
        },
        {
          "type": "STRING",
          "value": "struct"
        },
        {
          "type": "FIELD",
          "name": "body",
          "content": {
            "type": "SYMBOL",
            "name": "struct_body"
          }
        },
        {
          "type": "CHOICE",
          "members": [
            {
              "type": "STRING",
              "value": ";"
            },
            {
              "type": "BLANK"
            }
          ]
        }
      ]
    },
    "struct_body": {
      "type": "SEQ",
      "members": [
        {
          "type": "STRING",
          "value": "{"
        },
        {
          "type": "CHOICE",
          "members": [
            {
              "type": "REPEAT",
              "content": {
                "type": "CHOICE",
                "members": [
                  {
                    "type": "SYMBOL",
                    "name": "struct_field"
                  },
                  {
                    "type": "SYMBOL",
                    "name": "_statement"
                  }
                ]
              }
            },
            {
              "type": "BLANK"
            }
          ]
        },
        {
          "type": "STRING",
          "value": "}"
        }
      ]
    },
    "struct_field": {
      "type": "CHOICE",
      "members": [
        {
          "type": "SEQ",
          "members": [
            {
              "type": "FIELD",
              "name": "name",
              "content": {
                "type": "SYMBOL",
                "name": "identifier"
              }
            },
            {
              "type": "STRING",
              "value": ":"
            },
            {
              "type": "FIELD",
              "name": "type",
              "content": {
                "type": "SYMBOL",
                "name": "_type"
              }
            },
            {
              "type": "CHOICE",
              "members": [
                {
                  "type": "SEQ",
                  "members": [
                    {
                      "type": "STRING",
                      "value": "="
                    },
                    {
                      "type": "FIELD",
                      "name": "default_value",
                      "content": {
                        "type": "SYMBOL",
                        "name": "_expression"
                      }
                    }
                  ]
                },
                {
                  "type": "BLANK"
                }
              ]
            },
            {
              "type": "CHOICE",
              "members": [
                {
                  "type": "STRING",
                  "value": ","
                },
                {
                  "type": "BLANK"
                }
              ]
            },
            {
              "type": "STRING",
              "value": ";"
            }
          ]
        }
      ]
    },
    "enum_definition": {
      "type": "SEQ",
      "members": [
        {
          "type": "FIELD",
          "name": "name",
          "content": {
            "type": "SYMBOL",
            "name": "identifier"
          }
        },
        {
          "type": "STRING",
          "value": "::"
        },
        {
          "type": "CHOICE",
          "members": [
            {
              "type": "STRING",
              "value": "enum"
            },
            {
              "type": "STRING",
              "value": "enum_flags"
            }
          ]
        },
        {
          "type": "CHOICE",
          "members": [
            {
              "type": "SYMBOL",
              "name": "directive"
            },
            {
              "type": "BLANK"
            }
          ]
        },
        {
          "type": "FIELD",
          "name": "body",
          "content": {
            "type": "SYMBOL",
            "name": "enum_body"
          }
        },
        {
          "type": "CHOICE",
          "members": [
            {
              "type": "STRING",
              "value": ";"
            },
            {
              "type": "BLANK"
            }
          ]
        }
      ]
    },
    "enum_body": {
      "type": "SEQ",
      "members": [
        {
          "type": "STRING",
          "value": "{"
        },
        {
          "type": "REPEAT",
          "content": {
            "type": "SYMBOL",
            "name": "enum_values"
          }
        },
        {
          "type": "STRING",
          "value": "}"
        }
      ]
    },
    "enum_values": {
      "type": "SEQ",
      "members": [
        {
          "type": "FIELD",
          "name": "name",
          "content": {
            "type": "SYMBOL",
            "name": "identifier"
          }
        },
        {
          "type": "CHOICE",
          "members": [
            {
              "type": "SEQ",
              "members": [
                {
                  "type": "STRING",
                  "value": "::"
                },
                {
                  "type": "FIELD",
                  "name": "value",
                  "content": {
                    "type": "SYMBOL",
                    "name": "_expression"
                  }
                }
              ]
            },
            {
              "type": "BLANK"
            }
          ]
        },
        {
          "type": "STRING",
          "value": ";"
        }
      ]
    },
    "proc_definition": {
      "type": "SEQ",
      "members": [
        {
          "type": "FIELD",
          "name": "name",
          "content": {
            "type": "SYMBOL",
            "name": "identifier"
          }
        },
        {
          "type": "STRING",
          "value": "::"
        },
        {
          "type": "CHOICE",
          "members": [
            {
              "type": "REPEAT",
              "content": {
                "type": "CHOICE",
                "members": [
                  {
                    "type": "STRING",
                    "value": "inline"
                  }
                ]
              }
            },
            {
              "type": "BLANK"
            }
          ]
        },
        {
          "type": "SYMBOL",
          "name": "parameter_list"
        },
        {
          "type": "CHOICE",
          "members": [
            {
              "type": "SYMBOL",
              "name": "proc_return_expr"
            },
            {
              "type": "BLANK"
            }
          ]
        },
        {
          "type": "CHOICE",
          "members": [
            {
              "type": "REPEAT",
              "content": {
                "type": "SYMBOL",
                "name": "directive"
              }
            },
            {
              "type": "BLANK"
            }
          ]
        },
        {
          "type": "SYMBOL",
          "name": "block"
        }
      ]
    },
    "parameter_list": {
      "type": "SEQ",
      "members": [
        {
          "type": "STRING",
          "value": "("
        },
        {
          "type": "CHOICE",
          "members": [
            {
              "type": "SEQ",
              "members": [
                {
                  "type": "SYMBOL",
                  "name": "parameter"
                },
                {
                  "type": "REPEAT",
                  "content": {
                    "type": "SEQ",
                    "members": [
                      {
                        "type": "STRING",
                        "value": ","
                      },
                      {
                        "type": "SYMBOL",
                        "name": "parameter"
                      }
                    ]
                  }
                }
              ]
            },
            {
              "type": "BLANK"
            }
          ]
        },
        {
          "type": "STRING",
          "value": ")"
        }
      ]
    },
    "proc_return_expr": {
      "type": "PREC_LEFT",
      "value": 0,
      "content": {
        "type": "SEQ",
        "members": [
          {
            "type": "STRING",
            "value": "->"
          },
          {
            "type": "CHOICE",
            "members": [
              {
                "type": "STRING",
                "value": "("
              },
              {
                "type": "BLANK"
              }
            ]
          },
          {
            "type": "CHOICE",
            "members": [
              {
                "type": "SEQ",
                "members": [
                  {
                    "type": "SYMBOL",
                    "name": "proc_return_type_expr"
                  },
                  {
                    "type": "REPEAT",
                    "content": {
                      "type": "SEQ",
                      "members": [
                        {
                          "type": "STRING",
                          "value": ","
                        },
                        {
                          "type": "SYMBOL",
                          "name": "proc_return_type_expr"
                        }
                      ]
                    }
                  }
                ]
              },
              {
                "type": "BLANK"
              }
            ]
          },
          {
            "type": "CHOICE",
            "members": [
              {
                "type": "STRING",
                "value": ")"
              },
              {
                "type": "BLANK"
              }
            ]
          }
        ]
      }
    },
    "proc_return_type_expr": {
      "type": "PREC_LEFT",
      "value": 0,
      "content": {
        "type": "CHOICE",
        "members": [
          {
            "type": "FIELD",
            "name": "type",
            "content": {
              "type": "SYMBOL",
              "name": "_type"
            }
          },
          {
            "type": "SEQ",
            "members": [
              {
                "type": "FIELD",
                "name": "name",
                "content": {
                  "type": "SYMBOL",
                  "name": "identifier"
                }
              },
              {
                "type": "STRING",
                "value": ":"
              },
              {
                "type": "FIELD",
                "name": "type",
                "content": {
                  "type": "SYMBOL",
                  "name": "_type"
                }
              },
              {
                "type": "CHOICE",
                "members": [
                  {
                    "type": "SEQ",
                    "members": [
                      {
                        "type": "STRING",
                        "value": "="
                      },
                      {
                        "type": "FIELD",
                        "name": "default_value",
                        "content": {
                          "type": "SYMBOL",
                          "name": "_expression"
                        }
                      }
                    ]
                  },
                  {
                    "type": "BLANK"
                  }
                ]
              }
            ]
          }
        ]
      }
    },
    "block": {
      "type": "SEQ",
      "members": [
        {
          "type": "STRING",
          "value": "{"
        },
        {
          "type": "REPEAT",
          "content": {
            "type": "CHOICE",
            "members": [
              {
                "type": "SYMBOL",
                "name": "_statement"
              },
              {
                "type": "SYMBOL",
                "name": "if_directive"
              },
              {
                "type": "SYMBOL",
                "name": "if_case_directive"
              }
            ]
          }
        },
        {
          "type": "STRING",
          "value": "}"
        }
      ]
    },
    "_statement": {
      "type": "CHOICE",
      "members": [
        {
          "type": "SYMBOL",
          "name": "return_statement"
        },
        {
          "type": "SYMBOL",
          "name": "if_statement"
        },
        {
          "type": "SYMBOL",
          "name": "if_case"
        },
        {
          "type": "SYMBOL",
          "name": "for_statement"
        },
        {
          "type": "SYMBOL",
          "name": "while_statement"
        },
        {
          "type": "SYMBOL",
          "name": "case_statement"
        },
        {
          "type": "SYMBOL",
          "name": "break_statement"
        },
        {
          "type": "SYMBOL",
          "name": "continue_statement"
        },
        {
          "type": "SEQ",
          "members": [
            {
              "type": "SYMBOL",
              "name": "directive"
            },
            {
              "type": "STRING",
              "value": ";"
            }
          ]
        },
        {
          "type": "SYMBOL",
          "name": "constant"
        },
        {
          "type": "SYMBOL",
          "name": "variable"
        },
        {
          "type": "SYMBOL",
          "name": "expr_stmt"
        },
        {
          "type": "SYMBOL",
          "name": "defer_statement"
        },
        {
          "type": "SYMBOL",
          "name": "using_statement"
        },
        {
          "type": "SYMBOL",
          "name": "insert_directive"
        },
        {
          "type": "SYMBOL",
          "name": "assert_directive"
        }
      ]
    },
    "case_statement": {
      "type": "SEQ",
      "members": [
        {
          "type": "STRING",
          "value": "case"
        },
        {
          "type": "CHOICE",
          "members": [
            {
              "type": "FIELD",
              "name": "directive",
              "content": {
                "type": "SYMBOL",
                "name": "directive"
              }
            },
            {
              "type": "BLANK"
            }
          ]
        },
        {
          "type": "CHOICE",
          "members": [
            {
              "type": "SYMBOL",
              "name": "_expression"
            },
            {
              "type": "BLANK"
            }
          ]
        },
        {
          "type": "STRING",
          "value": ";"
        }
      ]
    },
    "break_statement": {
      "type": "SEQ",
      "members": [
        {
          "type": "STRING",
          "value": "break"
        },
        {
          "type": "CHOICE",
          "members": [
            {
              "type": "SEQ",
              "members": [
                {
                  "type": "STRING",
                  "value": ":"
                },
                {
                  "type": "SYMBOL",
                  "name": "identifier"
                }
              ]
            },
            {
              "type": "BLANK"
            }
          ]
        },
        {
          "type": "STRING",
          "value": ";"
        }
      ]
    },
    "continue_statement": {
      "type": "SEQ",
      "members": [
        {
          "type": "STRING",
          "value": "continue"
        },
        {
          "type": "STRING",
          "value": ";"
        }
      ]
    },
    "while_statement": {
      "type": "SEQ",
      "members": [
        {
          "type": "STRING",
          "value": "while"
        },
        {
          "type": "CHOICE",
          "members": [
            {
              "type": "SEQ",
              "members": [
                {
                  "type": "SYMBOL",
                  "name": "identifier"
                },
                {
                  "type": "STRING",
                  "value": ":"
                }
              ]
            },
            {
              "type": "BLANK"
            }
          ]
        },
        {
          "type": "FIELD",
          "name": "condition",
          "content": {
            "type": "SYMBOL",
            "name": "_expression"
          }
        },
        {
          "type": "CHOICE",
          "members": [
            {
              "type": "FIELD",
              "name": "body",
              "content": {
                "type": "SYMBOL",
                "name": "block"
              }
            },
            {
              "type": "FIELD",
              "name": "body",
              "content": {
                "type": "SYMBOL",
                "name": "_statement"
              }
            }
          ]
        }
      ]
    },
    "for_statement": {
      "type": "PREC_RIGHT",
      "value": 0,
      "content": {
        "type": "SEQ",
        "members": [
          {
            "type": "STRING",
            "value": "for"
          },
          {
            "type": "CHOICE",
            "members": [
              {
                "type": "SEQ",
                "members": [
                  {
                    "type": "SYMBOL",
                    "name": "identifier"
                  },
                  {
                    "type": "STRING",
                    "value": ":"
                  }
                ]
              },
              {
                "type": "BLANK"
              }
            ]
          },
          {
            "type": "SYMBOL",
            "name": "_expression"
          },
          {
            "type": "CHOICE",
            "members": [
              {
                "type": "FIELD",
                "name": "body",
                "content": {
                  "type": "SYMBOL",
                  "name": "block"
                }
              },
              {
                "type": "FIELD",
                "name": "body",
                "content": {
                  "type": "SYMBOL",
                  "name": "_statement"
                }
              }
            ]
          }
        ]
      }
    },
    "if_case": {
      "type": "SEQ",
      "members": [
        {
          "type": "STRING",
          "value": "if"
        },
        {
          "type": "FIELD",
          "name": "condition",
          "content": {
            "type": "SYMBOL",
            "name": "_expression"
          }
        },
        {
          "type": "STRING",
          "value": "=="
        },
        {
          "type": "SYMBOL",
          "name": "block"
        }
      ]
    },
    "if_case_directive": {
      "type": "PREC_RIGHT",
      "value": 0,
      "content": {
        "type": "SEQ",
        "members": [
          {
            "type": "STRING",
            "value": "#if"
          },
          {
            "type": "FIELD",
            "name": "condition",
            "content": {
              "type": "SYMBOL",
              "name": "_expression"
            }
          },
          {
            "type": "STRING",
            "value": "=="
          },
          {
            "type": "SEQ",
            "members": [
              {
                "type": "STRING",
                "value": "{"
              },
              {
                "type": "SEQ",
                "members": [
                  {
                    "type": "REPEAT",
                    "content": {
                      "type": "CHOICE",
                      "members": [
                        {
                          "type": "SYMBOL",
                          "name": "_statement"
                        },
                        {
                          "type": "SYMBOL",
                          "name": "_definition"
                        }
                      ]
                    }
                  }
                ]
              },
              {
                "type": "STRING",
                "value": "}"
              }
            ]
          }
        ]
      }
    },
    "if_directive": {
      "type": "PREC_RIGHT",
      "value": 1,
      "content": {
        "type": "SEQ",
        "members": [
          {
            "type": "STRING",
            "value": "#if"
          },
          {
            "type": "CHOICE",
            "members": [
              {
                "type": "STRING",
                "value": "("
              },
              {
                "type": "BLANK"
              }
            ]
          },
          {
            "type": "FIELD",
            "name": "condition",
            "content": {
              "type": "SYMBOL",
              "name": "_expression"
            }
          },
          {
            "type": "CHOICE",
            "members": [
              {
                "type": "STRING",
                "value": ")"
              },
              {
                "type": "BLANK"
              }
            ]
          },
          {
            "type": "CHOICE",
            "members": [
              {
                "type": "STRING",
                "value": "then"
              },
              {
                "type": "BLANK"
              }
            ]
          },
          {
            "type": "CHOICE",
            "members": [
              {
                "type": "FIELD",
                "name": "then_branch",
                "content": {
                  "type": "SYMBOL",
                  "name": "block"
                }
              },
              {
                "type": "FIELD",
                "name": "then_branch",
                "content": {
                  "type": "SYMBOL",
                  "name": "_definition"
                }
              },
              {
                "type": "FIELD",
                "name": "then_branch",
                "content": {
                  "type": "SYMBOL",
                  "name": "_statement"
                }
              }
            ]
          },
          {
            "type": "CHOICE",
            "members": [
              {
                "type": "SEQ",
                "members": [
                  {
                    "type": "STRING",
                    "value": "else"
                  },
                  {
                    "type": "FIELD",
                    "name": "else_branch",
                    "content": {
                      "type": "CHOICE",
                      "members": [
                        {
                          "type": "SYMBOL",
                          "name": "_definition"
                        },
                        {
                          "type": "SYMBOL",
                          "name": "_statement"
                        }
                      ]
                    }
                  }
                ]
              },
              {
                "type": "BLANK"
              }
            ]
          }
        ]
      }
    },
    "if_statement": {
      "type": "PREC_RIGHT",
      "value": 0,
      "content": {
        "type": "SEQ",
        "members": [
          {
            "type": "STRING",
            "value": "if"
          },
          {
            "type": "CHOICE",
            "members": [
              {
                "type": "STRING",
                "value": "("
              },
              {
                "type": "BLANK"
              }
            ]
          },
          {
            "type": "FIELD",
            "name": "condition",
            "content": {
              "type": "SYMBOL",
              "name": "_expression"
            }
          },
          {
            "type": "CHOICE",
            "members": [
              {
                "type": "STRING",
                "value": ")"
              },
              {
                "type": "BLANK"
              }
            ]
          },
          {
            "type": "CHOICE",
            "members": [
              {
                "type": "STRING",
                "value": "then"
              },
              {
                "type": "BLANK"
              }
            ]
          },
          {
            "type": "CHOICE",
            "members": [
              {
                "type": "FIELD",
                "name": "then_branch",
                "content": {
                  "type": "SYMBOL",
                  "name": "block"
                }
              },
              {
                "type": "FIELD",
                "name": "then_branch",
                "content": {
                  "type": "SYMBOL",
                  "name": "_statement"
                }
              }
            ]
          },
          {
            "type": "CHOICE",
            "members": [
              {
                "type": "SEQ",
                "members": [
                  {
                    "type": "STRING",
                    "value": "else"
                  },
                  {
                    "type": "FIELD",
                    "name": "else_branch",
                    "content": {
                      "type": "CHOICE",
                      "members": [
                        {
                          "type": "SYMBOL",
                          "name": "block"
                        },
                        {
                          "type": "SYMBOL",
                          "name": "if_statement"
                        },
                        {
                          "type": "SYMBOL",
                          "name": "_statement"
                        }
                      ]
                    }
                  }
                ]
              },
              {
                "type": "BLANK"
              }
            ]
          }
        ]
      }
    },
    "ifx_expr": {
      "type": "PREC_RIGHT",
      "value": 1,
      "content": {
        "type": "SEQ",
        "members": [
          {
            "type": "FIELD",
            "name": "keyword",
            "content": {
              "type": "STRING",
              "value": "ifx"
            }
          },
          {
            "type": "CHOICE",
            "members": [
              {
                "type": "STRING",
                "value": "("
              },
              {
                "type": "BLANK"
              }
            ]
          },
          {
            "type": "FIELD",
            "name": "condition",
            "content": {
              "type": "SYMBOL",
              "name": "_expression"
            }
          },
          {
            "type": "CHOICE",
            "members": [
              {
                "type": "STRING",
                "value": ")"
              },
              {
                "type": "BLANK"
              }
            ]
          },
          {
            "type": "CHOICE",
            "members": [
              {
                "type": "FIELD",
                "name": "keyword",
                "content": {
                  "type": "STRING",
                  "value": "then"
                }
              },
              {
                "type": "BLANK"
              }
            ]
          },
          {
            "type": "CHOICE",
            "members": [
              {
                "type": "FIELD",
                "name": "then_branch",
                "content": {
                  "type": "SYMBOL",
                  "name": "_expression"
                }
              }
            ]
          },
          {
            "type": "CHOICE",
            "members": [
              {
                "type": "SEQ",
                "members": [
                  {
                    "type": "STRING",
                    "value": "else"
                  },
                  {
                    "type": "FIELD",
                    "name": "else_branch",
                    "content": {
                      "type": "CHOICE",
                      "members": [
                        {
                          "type": "SYMBOL",
                          "name": "_expression"
                        }
                      ]
                    }
                  }
                ]
              },
              {
                "type": "BLANK"
              }
            ]
          }
        ]
      }
    },
    "using_statement": {
      "type": "SEQ",
      "members": [
        {
          "type": "STRING",
          "value": "using"
        },
        {
          "type": "SYMBOL",
          "name": "_statement"
        }
      ]
    },
    "return_statement": {
      "type": "SEQ",
      "members": [
        {
          "type": "STRING",
          "value": "return"
        },
        {
          "type": "CHOICE",
          "members": [
            {
              "type": "CHOICE",
              "members": [
                {
                  "type": "SYMBOL",
                  "name": "_expression"
                },
                {
                  "type": "SEQ",
                  "members": [
                    {
                      "type": "SYMBOL",
                      "name": "_expression"
                    },
                    {
                      "type": "REPEAT",
                      "content": {
                        "type": "SEQ",
                        "members": [
                          {
                            "type": "STRING",
                            "value": ","
                          },
                          {
                            "type": "SYMBOL",
                            "name": "_expression"
                          }
                        ]
                      }
                    }
                  ]
                },
                {
                  "type": "SEQ",
                  "members": [
                    {
                      "type": "SYMBOL",
                      "name": "named_return_expr"
                    },
                    {
                      "type": "REPEAT",
                      "content": {
                        "type": "SEQ",
                        "members": [
                          {
                            "type": "STRING",
                            "value": ","
                          },
                          {
                            "type": "SYMBOL",
                            "name": "named_return_expr"
                          }
                        ]
                      }
                    }
                  ]
                }
              ]
            },
            {
              "type": "BLANK"
            }
          ]
        },
        {
          "type": "STRING",
          "value": ";"
        }
      ]
    },
    "named_return_expr": {
      "type": "SEQ",
      "members": [
        {
          "type": "FIELD",
          "name": "name",
          "content": {
            "type": "SYMBOL",
            "name": "identifier"
          }
        },
        {
          "type": "STRING",
          "value": "="
        },
        {
          "type": "SYMBOL",
          "name": "_expression"
        }
      ]
    },
    "expr_stmt": {
      "type": "SEQ",
      "members": [
        {
          "type": "CHOICE",
          "members": [
            {
              "type": "SYMBOL",
              "name": "_expression"
            },
            {
              "type": "SYMBOL",
              "name": "assignment_expression"
            }
          ]
        },
        {
          "type": "STRING",
          "value": ";"
        }
      ]
    },
    "assignment_expression": {
      "type": "SEQ",
      "members": [
        {
          "type": "FIELD",
          "name": "left",
          "content": {
            "type": "CHOICE",
            "members": [
              {
                "type": "SEQ",
                "members": [
                  {
                    "type": "SYMBOL",
                    "name": "identifier"
                  },
                  {
                    "type": "CHOICE",
                    "members": [
                      {
                        "type": "SEQ",
                        "members": [
                          {
                            "type": "STRING",
                            "value": ":"
                          },
                          {
                            "type": "SYMBOL",
                            "name": "_type"
                          }
                        ]
                      },
                      {
                        "type": "BLANK"
                      }
                    ]
                  }
                ]
              },
              {
                "type": "SYMBOL",
                "name": "member_access_expr"
              },
              {
                "type": "SYMBOL",
                "name": "dereference"
              }
            ]
          }
        },
        {
          "type": "CHOICE",
          "members": [
            {
              "type": "SEQ",
              "members": [
                {
                  "type": "FIELD",
                  "name": "operator",
                  "content": {
                    "type": "CHOICE",
                    "members": [
                      {
                        "type": "STRING",
                        "value": "="
                      },
                      {
                        "type": "STRING",
                        "value": "+="
                      },
                      {
                        "type": "STRING",
                        "value": "-="
                      },
                      {
                        "type": "STRING",
                        "value": "*="
                      },
                      {
                        "type": "STRING",
                        "value": "/="
                      },
                      {
                        "type": "STRING",
                        "value": "%="
                      }
                    ]
                  }
                },
                {
                  "type": "FIELD",
                  "name": "right",
                  "content": {
                    "type": "SYMBOL",
                    "name": "_expression"
                  }
                }
              ]
            },
            {
              "type": "BLANK"
            }
          ]
        }
      ]
    },
    "defer_statement": {
      "type": "SEQ",
      "members": [
        {
          "type": "STRING",
          "value": "defer"
        },
        {
          "type": "CHOICE",
          "members": [
            {
              "type": "SYMBOL",
              "name": "expr_stmt"
            },
            {
              "type": "SYMBOL",
              "name": "block"
            }
          ]
        }
      ]
    },
    "proc_call_expr": {
      "type": "SEQ",
      "members": [
        {
          "type": "CHOICE",
          "members": [
            {
              "type": "REPEAT",
              "content": {
                "type": "SEQ",
                "members": [
                  {
                    "type": "FIELD",
                    "name": "object",
                    "content": {
                      "type": "SYMBOL",
                      "name": "identifier"
                    }
                  },
                  {
                    "type": "STRING",
                    "value": "."
                  }
                ]
              }
            },
            {
              "type": "BLANK"
            }
          ]
        },
        {
          "type": "FIELD",
          "name": "function",
          "content": {
            "type": "SYMBOL",
            "name": "identifier"
          }
        },
        {
          "type": "FIELD",
          "name": "arguments",
          "content": {
            "type": "SYMBOL",
            "name": "argument_list"
          }
        }
      ]
    },
    "argument_list": {
      "type": "SEQ",
      "members": [
        {
          "type": "STRING",
          "value": "("
        },
        {
          "type": "CHOICE",
          "members": [
            {
              "type": "CHOICE",
              "members": [
                {
                  "type": "SEQ",
                  "members": [
                    {
                      "type": "SYMBOL",
                      "name": "_expression"
                    },
                    {
                      "type": "REPEAT",
                      "content": {
                        "type": "CHOICE",
                        "members": [
                          {
                            "type": "SEQ",
                            "members": [
                              {
                                "type": "STRING",
                                "value": ","
                              },
                              {
                                "type": "SYMBOL",
                                "name": "_expression"
                              }
                            ]
                          },
                          {
                            "type": "SEQ",
                            "members": [
                              {
                                "type": "STRING",
                                "value": ".."
                              },
                              {
                                "type": "SYMBOL",
                                "name": "identifier"
                              }
                            ]
                          }
                        ]
                      }
                    }
                  ]
                },
                {
                  "type": "BLANK"
                }
              ]
            },
            {
              "type": "SEQ",
              "members": [
                {
                  "type": "STRING",
                  "value": ".."
                },
                {
                  "type": "SYMBOL",
                  "name": "identifier"
                }
              ]
            }
          ]
        },
        {
          "type": "STRING",
          "value": ")"
        }
      ]
    },
    "_type": {
      "type": "PREC",
      "value": 10,
      "content": {
        "type": "CHOICE",
        "members": [
          {
            "type": "STRING",
            "value": "bool"
          },
          {
            "type": "STRING",
            "value": "string"
          },
          {
            "type": "STRING",
            "value": "int"
          },
          {
            "type": "STRING",
            "value": "float"
          },
          {
            "type": "STRING",
            "value": "float64"
          },
          {
            "type": "STRING",
            "value": "float32"
          },
          {
            "type": "STRING",
            "value": "s64"
          },
          {
            "type": "STRING",
            "value": "s32"
          },
          {
            "type": "STRING",
            "value": "s16"
          },
          {
            "type": "STRING",
            "value": "s8"
          },
          {
            "type": "STRING",
            "value": "u64"
          },
          {
            "type": "STRING",
            "value": "u32"
          },
          {
            "type": "STRING",
            "value": "u16"
          },
          {
            "type": "STRING",
            "value": "u8"
          },
          {
            "type": "STRING",
            "value": "void"
          },
          {
            "type": "STRING",
            "value": "Any"
          },
          {
            "type": "STRING",
            "value": "Type"
          },
          {
            "type": "STRING",
            "value": "Context"
          },
          {
            "type": "SYMBOL",
            "name": "identifier"
          },
          {
            "type": "SEQ",
            "members": [
              {
                "type": "STRING",
                "value": "["
              },
              {
                "type": "CHOICE",
                "members": [
                  {
                    "type": "CHOICE",
                    "members": [
                      {
                        "type": "SYMBOL",
                        "name": "_expression"
                      },
                      {
                        "type": "BLANK"
                      }
                    ]
                  },
                  {
                    "type": "STRING",
                    "value": ".."
                  }
                ]
              },
              {
                "type": "STRING",
                "value": "]"
              },
              {
                "type": "SYMBOL",
                "name": "_type"
              }
            ]
          },
          {
            "type": "SEQ",
            "members": [
              {
                "type": "STRING",
                "value": "*"
              },
              {
                "type": "SYMBOL",
                "name": "_type"
              }
            ]
          },
          {
            "type": "SYMBOL",
            "name": "proc_decl"
          }
        ]
      }
    },
    "proc_decl": {
      "type": "PREC_LEFT",
      "value": 10,
      "content": {
        "type": "SEQ",
        "members": [
          {
            "type": "SYMBOL",
            "name": "parameter_list"
          },
          {
            "type": "CHOICE",
            "members": [
              {
                "type": "SYMBOL",
                "name": "proc_return_expr"
              },
              {
                "type": "BLANK"
              }
            ]
          },
          {
            "type": "CHOICE",
            "members": [
              {
                "type": "REPEAT",
                "content": {
                  "type": "SYMBOL",
                  "name": "directive"
                }
              },
              {
                "type": "BLANK"
              }
            ]
          }
        ]
      }
    },
    "constant": {
      "type": "CHOICE",
      "members": [
        {
          "type": "SEQ",
          "members": [
            {
              "type": "SYMBOL",
              "name": "identifier"
            },
            {
              "type": "STRING",
              "value": "::"
            },
            {
              "type": "SYMBOL",
              "name": "_expression"
            },
            {
              "type": "STRING",
              "value": ";"
            }
          ]
        },
        {
          "type": "SEQ",
          "members": [
            {
              "type": "SYMBOL",
              "name": "identifier"
            },
            {
              "type": "STRING",
              "value": ":"
            },
            {
              "type": "SYMBOL",
              "name": "_type"
            },
            {
              "type": "STRING",
              "value": ":"
            },
            {
              "type": "SYMBOL",
              "name": "_expression"
            },
            {
              "type": "STRING",
              "value": ";"
            }
          ]
        },
        {
          "type": "SEQ",
          "members": [
            {
              "type": "SYMBOL",
              "name": "identifier"
            },
            {
              "type": "STRING",
              "value": "::"
            },
            {
              "type": "SYMBOL",
              "name": "code_directive"
            }
          ]
        }
      ]
    },
    "code_directive": {
      "type": "SEQ",
      "members": [
        {
          "type": "FIELD",
          "name": "name",
          "content": {
            "type": "STRING",
            "value": "#code"
          }
        },
        {
          "type": "SYMBOL",
          "name": "block"
        }
      ]
    },
    "insert_directive": {
      "type": "SEQ",
      "members": [
        {
          "type": "STRING",
          "value": "#insert"
        },
        {
          "type": "SYMBOL",
          "name": "identifier"
        },
        {
          "type": "STRING",
          "value": ";"
        }
      ]
    },
    "assert_directive": {
      "type": "SEQ",
      "members": [
        {
          "type": "STRING",
          "value": "#assert"
        },
        {
          "type": "FIELD",
          "name": "arguments",
          "content": {
            "type": "SYMBOL",
            "name": "argument_list"
          }
        },
        {
          "type": "STRING",
          "value": ";"
        }
      ]
    },
    "variable": {
      "type": "CHOICE",
      "members": [
        {
          "type": "SEQ",
          "members": [
            {
              "type": "SYMBOL",
              "name": "identifier"
            },
            {
              "type": "STRING",
              "value": ":="
            },
            {
              "type": "SYMBOL",
              "name": "_expression"
            },
            {
              "type": "STRING",
              "value": ";"
            }
          ]
        },
        {
          "type": "SEQ",
          "members": [
            {
              "type": "SYMBOL",
              "name": "identifier"
            },
            {
              "type": "STRING",
              "value": ":"
            },
            {
              "type": "SYMBOL",
              "name": "_type"
            },
            {
              "type": "STRING",
              "value": "="
            },
            {
              "type": "SYMBOL",
              "name": "_expression"
            },
            {
              "type": "STRING",
              "value": ";"
            }
          ]
        }
      ]
    },
    "parameter": {
      "type": "CHOICE",
      "members": [
        {
          "type": "SEQ",
          "members": [
            {
              "type": "CHOICE",
              "members": [
                {
                  "type": "SYMBOL",
                  "name": "using"
                },
                {
                  "type": "BLANK"
                }
              ]
            },
            {
              "type": "CHOICE",
              "members": [
                {
                  "type": "STRING",
                  "value": "$"
                },
                {
                  "type": "BLANK"
                }
              ]
            },
            {
              "type": "FIELD",
              "name": "name",
              "content": {
                "type": "SYMBOL",
                "name": "identifier"
              }
            },
            {
              "type": "STRING",
              "value": ":"
            },
            {
              "type": "CHOICE",
              "members": [
                {
                  "type": "STRING",
                  "value": "$"
                },
                {
                  "type": "BLANK"
                }
              ]
            },
            {
              "type": "FIELD",
              "name": "type",
              "content": {
                "type": "SYMBOL",
                "name": "_type"
              }
            },
            {
              "type": "CHOICE",
              "members": [
                {
                  "type": "SEQ",
                  "members": [
                    {
                      "type": "STRING",
                      "value": "="
                    },
                    {
                      "type": "SYMBOL",
                      "name": "_expression"
                    }
                  ]
                },
                {
                  "type": "BLANK"
                }
              ]
            }
          ]
        },
        {
          "type": "SEQ",
          "members": [
            {
              "type": "CHOICE",
              "members": [
                {
                  "type": "SYMBOL",
                  "name": "using"
                },
                {
                  "type": "BLANK"
                }
              ]
            },
            {
              "type": "CHOICE",
              "members": [
                {
                  "type": "STRING",
                  "value": "$"
                },
                {
                  "type": "BLANK"
                }
              ]
            },
            {
              "type": "FIELD",
              "name": "name",
              "content": {
                "type": "SYMBOL",
                "name": "identifier"
              }
            },
            {
              "type": "STRING",
              "value": ":="
            },
            {
              "type": "CHOICE",
              "members": [
                {
                  "type": "SYMBOL",
                  "name": "_expression"
                },
                {
                  "type": "STRING",
                  "value": "#caller_location"
                }
              ]
            }
          ]
        },
        {
          "type": "SEQ",
          "members": [
            {
              "type": "FIELD",
              "name": "name",
              "content": {
                "type": "SYMBOL",
                "name": "identifier"
              }
            },
            {
              "type": "STRING",
              "value": ":"
            },
            {
              "type": "STRING",
              "value": ".."
            },
            {
              "type": "FIELD",
              "name": "type",
              "content": {
                "type": "SYMBOL",
                "name": "_type"
              }
            }
          ]
        }
      ]
    },
    "import_directive": {
      "type": "SEQ",
      "members": [
        {
          "type": "CHOICE",
          "members": [
            {
              "type": "SEQ",
              "members": [
                {
                  "type": "FIELD",
                  "name": "name",
                  "content": {
                    "type": "SYMBOL",
                    "name": "identifier"
                  }
                },
                {
                  "type": "STRING",
                  "value": "::"
                }
              ]
            },
            {
              "type": "BLANK"
            }
          ]
        },
        {
          "type": "CHOICE",
          "members": [
            {
              "type": "STRING",
              "value": "#import"
            },
            {
              "type": "STRING",
              "value": "#load"
            }
          ]
        },
        {
          "type": "STRING",
          "value": "\""
        },
        {
          "type": "FIELD",
          "name": "path",
          "content": {
            "type": "SYMBOL",
            "name": "string_content"
          }
        },
        {
          "type": "STRING",
          "value": "\""
        },
        {
          "type": "CHOICE",
          "members": [
            {
              "type": "SEQ",
              "members": [
                {
                  "type": "STRING",
                  "value": "("
                },
                {
                  "type": "STRING",
                  "value": ")"
                }
              ]
            },
            {
              "type": "BLANK"
            }
          ]
        },
        {
          "type": "CHOICE",
          "members": [
            {
              "type": "SEQ",
              "members": [
                {
                  "type": "STRING",
                  "value": "("
                },
                {
                  "type": "SYMBOL",
                  "name": "identifier"
                },
                {
                  "type": "STRING",
                  "value": "="
                },
                {
                  "type": "SYMBOL",
                  "name": "_expression"
                },
                {
                  "type": "STRING",
                  "value": ")"
                }
              ]
            },
            {
              "type": "BLANK"
            }
          ]
        },
        {
          "type": "STRING",
          "value": ";"
        }
      ]
    },
    "comment": {
      "type": "TOKEN",
      "content": {
        "type": "CHOICE",
        "members": [
          {
            "type": "SEQ",
            "members": [
              {
                "type": "STRING",
                "value": "//"
              },
              {
                "type": "PATTERN",
                "value": ".*"
              }
            ]
          },
          {
            "type": "SEQ",
            "members": [
              {
                "type": "STRING",
                "value": "/*"
              },
              {
                "type": "PATTERN",
                "value": "[^*]*\\*+([^/*][^*]*\\*+)*"
              },
              {
                "type": "STRING",
                "value": "/"
              }
            ]
          }
        ]
      }
    },
    "_expression": {
      "type": "CHOICE",
      "members": [
        {
          "type": "SYMBOL",
          "name": "identifier"
        },
        {
          "type": "SYMBOL",
          "name": "number"
        },
        {
          "type": "SYMBOL",
          "name": "float"
        },
        {
          "type": "SYMBOL",
          "name": "string"
        },
        {
          "type": "SYMBOL",
          "name": "boolean"
        },
        {
          "type": "SYMBOL",
          "name": "null"
        },
        {
          "type": "SYMBOL",
          "name": "proc_call_expr"
        },
        {
          "type": "SYMBOL",
          "name": "binary_expression"
        },
        {
          "type": "SYMBOL",
          "name": "unary_expression"
        },
        {
          "type": "SYMBOL",
          "name": "parenthesized_expression"
        },
        {
          "type": "SYMBOL",
          "name": "struct_literal_expr"
        },
        {
          "type": "SYMBOL",
          "name": "enum_value_expr"
        },
        {
          "type": "SYMBOL",
          "name": "member_access_expr"
        },
        {
          "type": "SYMBOL",
          "name": "range_expr"
        },
        {
          "type": "SYMBOL",
          "name": "undefined"
        },
        {
          "type": "SYMBOL",
          "name": "dereference"
        },
        {
          "type": "SYMBOL",
          "name": "auto_cast_expr"
        },
        {
          "type": "SYMBOL",
          "name": "array_access"
        },
        {
          "type": "SYMBOL",
          "name": "ifx_expr"
        },
        {
          "type": "SYMBOL",
          "name": "char_expr"
        }
      ]
    },
    "char_expr": {
      "type": "SEQ",
      "members": [
        {
          "type": "STRING",
          "value": "#char"
        },
        {
          "type": "SYMBOL",
          "name": "string"
        }
      ]
    },
    "array_access": {
      "type": "SEQ",
      "members": [
        {
          "type": "SYMBOL",
          "name": "identifier"
        },
        {
          "type": "STRING",
          "value": "["
        },
        {
          "type": "SYMBOL",
          "name": "_expression"
        },
        {
          "type": "STRING",
          "value": "]"
        }
      ]
    },
    "auto_cast_expr": {
      "type": "SEQ",
      "members": [
        {
          "type": "STRING",
          "value": "xx"
        },
        {
          "type": "SYMBOL",
          "name": "_expression"
        }
      ]
    },
    "dereference": {
      "type": "SEQ",
      "members": [
        {
          "type": "SYMBOL",
          "name": "identifier"
        },
        {
          "type": "STRING",
          "value": "."
        },
        {
          "type": "STRING",
          "value": "*"
        }
      ]
    },
    "undefined": {
      "type": "STRING",
      "value": "---"
    },
    "range_expr": {
      "type": "PREC_RIGHT",
      "value": 2,
      "content": {
        "type": "SEQ",
        "members": [
          {
            "type": "SYMBOL",
            "name": "_expression"
          },
          {
            "type": "STRING",
            "value": ".."
          },
          {
            "type": "SYMBOL",
            "name": "_expression"
          }
        ]
      }
    },
    "member_access_expr": {
      "type": "PREC",
      "value": 6,
      "content": {
        "type": "SEQ",
        "members": [
          {
            "type": "FIELD",
            "name": "object",
            "content": {
              "type": "SYMBOL",
              "name": "_expression"
            }
          },
          {
            "type": "STRING",
            "value": "."
          },
          {
            "type": "FIELD",
            "name": "property",
            "content": {
              "type": "SYMBOL",
              "name": "identifier"
            }
          }
        ]
      }
    },
    "enum_value_expr": {
      "type": "PREC_LEFT",
      "value": 0,
      "content": {
        "type": "CHOICE",
        "members": [
          {
            "type": "SEQ",
            "members": [
              {
                "type": "SYMBOL",
                "name": "identifier"
              },
              {
                "type": "STRING",
                "value": "."
              },
              {
                "type": "SYMBOL",
                "name": "identifier"
              }
            ]
          },
          {
            "type": "SEQ",
            "members": [
              {
                "type": "STRING",
                "value": "."
              },
              {
                "type": "FIELD",
                "name": "name",
                "content": {
                  "type": "SYMBOL",
                  "name": "identifier"
                }
              }
            ]
          }
        ]
      }
    },
    "struct_literal_expr": {
      "type": "SEQ",
      "members": [
        {
          "type": "CHOICE",
          "members": [
            {
              "type": "SEQ",
              "members": [
                {
                  "type": "SYMBOL",
                  "name": "identifier"
                },
                {
                  "type": "REPEAT",
                  "content": {
                    "type": "SEQ",
                    "members": [
                      {
                        "type": "STRING",
                        "value": "."
                      },
                      {
                        "type": "SYMBOL",
                        "name": "identifier"
                      }
                    ]
                  }
                }
              ]
            },
            {
              "type": "BLANK"
            }
          ]
        },
        {
          "type": "STRING",
          "value": "."
        },
        {
          "type": "STRING",
          "value": "{"
        },
        {
          "type": "CHOICE",
          "members": [
            {
              "type": "CHOICE",
              "members": [
                {
                  "type": "SYMBOL",
                  "name": "struct_initialize_with_field"
                },
                {
                  "type": "SEQ",
                  "members": [
                    {
                      "type": "SYMBOL",
                      "name": "struct_initialize_without_field"
                    }
                  ]
                }
              ]
            },
            {
              "type": "BLANK"
            }
          ]
        },
        {
          "type": "STRING",
          "value": "}"
        }
      ]
    },
    "struct_initialize_without_field": {
      "type": "SEQ",
      "members": [
        {
          "type": "SYMBOL",
          "name": "_expression"
        },
        {
          "type": "REPEAT",
          "content": {
            "type": "SEQ",
            "members": [
              {
                "type": "STRING",
                "value": ","
              },
              {
                "type": "SYMBOL",
                "name": "_expression"
              }
            ]
          }
        }
      ]
    },
    "struct_initialize_with_field": {
      "type": "SEQ",
      "members": [
        {
          "type": "SYMBOL",
          "name": "identifier"
        },
        {
          "type": "STRING",
          "value": "="
        },
        {
          "type": "SYMBOL",
          "name": "_expression"
        },
        {
          "type": "REPEAT",
          "content": {
            "type": "SEQ",
            "members": [
              {
                "type": "STRING",
                "value": ","
              },
              {
                "type": "SEQ",
                "members": [
                  {
                    "type": "SYMBOL",
                    "name": "identifier"
                  },
                  {
                    "type": "STRING",
                    "value": "="
                  },
                  {
                    "type": "SYMBOL",
                    "name": "_expression"
                  }
                ]
              }
            ]
          }
        },
        {
          "type": "CHOICE",
          "members": [
            {
              "type": "STRING",
              "value": ","
            },
            {
              "type": "BLANK"
            }
          ]
        }
      ]
    },
    "binary_expression": {
      "type": "PREC_LEFT",
      "value": 1,
      "content": {
        "type": "SEQ",
        "members": [
          {
            "type": "FIELD",
            "name": "left",
            "content": {
              "type": "SYMBOL",
              "name": "_expression"
            }
          },
          {
            "type": "FIELD",
            "name": "operator",
            "content": {
              "type": "CHOICE",
              "members": [
                {
                  "type": "STRING",
                  "value": "+"
                },
                {
                  "type": "STRING",
                  "value": "-"
                },
                {
                  "type": "STRING",
                  "value": "*"
                },
                {
                  "type": "STRING",
                  "value": "/"
                },
                {
                  "type": "STRING",
                  "value": "%"
                },
                {
                  "type": "STRING",
                  "value": "=="
                },
                {
                  "type": "STRING",
                  "value": "!="
                },
                {
                  "type": "STRING",
                  "value": "<"
                },
                {
                  "type": "STRING",
                  "value": "<="
                },
                {
                  "type": "STRING",
                  "value": ">"
                },
                {
                  "type": "STRING",
                  "value": ">="
                },
                {
                  "type": "STRING",
                  "value": "&&"
                },
                {
                  "type": "STRING",
                  "value": "||"
                },
                {
                  "type": "STRING",
                  "value": "&"
                },
                {
                  "type": "STRING",
                  "value": "|"
                },
                {
                  "type": "STRING",
                  "value": "^"
                },
                {
                  "type": "STRING",
                  "value": "<<"
                },
                {
                  "type": "STRING",
                  "value": ">>"
                }
              ]
            }
          },
          {
            "type": "FIELD",
            "name": "right",
            "content": {
              "type": "SYMBOL",
              "name": "_expression"
            }
          }
        ]
      }
    },
    "unary_expression": {
      "type": "PREC_RIGHT",
      "value": 3,
      "content": {
        "type": "SEQ",
        "members": [
          {
            "type": "FIELD",
            "name": "operator",
            "content": {
              "type": "CHOICE",
              "members": [
                {
                  "type": "STRING",
                  "value": "-"
                },
                {
                  "type": "STRING",
                  "value": "!"
                },
                {
                  "type": "STRING",
                  "value": "~"
                },
                {
                  "type": "STRING",
                  "value": "*"
                },
                {
                  "type": "STRING",
                  "value": "&"
                }
              ]
            }
          },
          {
            "type": "FIELD",
            "name": "argument",
            "content": {
              "type": "SYMBOL",
              "name": "_expression"
            }
          }
        ]
      }
    },
    "parenthesized_expression": {
      "type": "SEQ",
      "members": [
        {
          "type": "STRING",
          "value": "("
        },
        {
          "type": "SYMBOL",
          "name": "_expression"
        },
        {
          "type": "STRING",
          "value": ")"
        }
      ]
    },
    "directive": {
      "type": "SEQ",
      "members": [
        {
          "type": "STRING",
          "value": "#"
        },
        {
          "type": "SYMBOL",
          "name": "identifier"
        }
      ]
    },
    "using": {
      "type": "STRING",
      "value": "using"
    },
    "string_content": {
      "type": "TOKEN",
      "content": {
        "type": "PATTERN",
        "value": "([^\"\\\\]|\\\\.)*"
      }
    },
    "identifier": {
      "type": "PATTERN",
      "value": "[a-zA-Z_]\\w*"
    },
    "number": {
      "type": "PATTERN",
      "value": "[\\d_]+"
    },
    "float": {
      "type": "PATTERN",
      "value": "\\d+\\.\\d+"
    },
    "string": {
      "type": "SEQ",
      "members": [
        {
          "type": "STRING",
          "value": "\""
        },
        {
          "type": "CHOICE",
          "members": [
            {
              "type": "SYMBOL",
              "name": "string_content"
            },
            {
              "type": "BLANK"
            }
          ]
        },
        {
          "type": "STRING",
          "value": "\""
        }
      ]
    },
    "boolean": {
      "type": "CHOICE",
      "members": [
        {
          "type": "STRING",
          "value": "true"
        },
        {
          "type": "STRING",
          "value": "false"
        }
      ]
    },
    "null": {
      "type": "STRING",
      "value": "null"
    }
  },
  "extras": [
    {
      "type": "PATTERN",
      "value": "\\s"
    },
    {
      "type": "SYMBOL",
      "name": "comment"
    }
  ],
  "conflicts": [
    [
      "struct_body",
      "enum_body"
    ],
    [
      "assignment_expression",
      "variable"
    ],
    [
      "proc_call_expr",
      "enum_value_expr"
    ],
    [
      "proc_call_expr",
      "enum_value_expr",
      "_expression",
      "struct_literal_expr"
    ],
    [
      "proc_call_expr",
      "_expression"
    ],
    [
      "if_statement",
      "parenthesized_expression"
    ],
    [
      "_statement",
      "if_statement"
    ],
    [
      "parameter",
      "_expression"
    ],
    [
      "assignment_expression",
      "_expression"
    ],
    [
      "proc_call_expr",
      "enum_value_expr",
      "struct_literal_expr"
    ],
    [
      "enum_value_expr",
      "struct_literal_expr"
    ],
    [
      "case_statement",
      "_expression"
    ],
    [
      "argument_list",
      "_expression"
    ],
    [
      "proc_call_expr",
      "_expression",
      "dereference",
      "enum_value_expr",
      "struct_literal_expr"
    ],
    [
      "parameter_list",
      "proc_return_expr"
    ],
    [
      "proc_return_type_expr",
      "parameter"
    ],
    [
      "struct_field",
      "assignment_expression"
    ],
    [
      "struct_field",
      "assignment_expression",
      "variable"
    ],
    [
      "struct_field",
      "variable"
    ]
  ],
  "precedences": [],
  "externals": [],
  "inline": [],
  "supertypes": [],
  "reserved": {}
}